grPyHole-0.9.2.dist-info/DESCRIPTION.rst
grPyHole-0.9.2.dist-info/METADATA
grPyHole-0.9.2.dist-info/RECORD
grPyHole-0.9.2.dist-info/WHEEL
grPyHole-0.9.2.dist-info/metadata.json
grPyHole-0.9.2.dist-info/top_level.txt
gr_pyhole/__init__.py
gr_pyhole/display.py
gr_pyhole/image.py
gr_pyhole/scene.py
gr_pyhole/CL/CFlat.cl
gr_pyhole/CL/CHR.cl
gr_pyhole/CL/Flat.cl
gr_pyhole/CL/HR.cl
gr_pyhole/CL/Kerr.cl
gr_pyhole/CL/RHS-C.cl
gr_pyhole/CL/RHS.cl
gr_pyhole/CL/RK.cl
gr_pyhole/CL/RK.h
gr_pyhole/CL/RKF23.h
gr_pyhole/CL/RKF45.h
gr_pyhole/CL/RKF56.h
gr_pyhole/CL/RKF67.h
gr_pyhole/CL/RKF78.h
gr_pyhole/CL/RKF89.h
gr_pyhole/CL/Schwarzschild.cl
gr_pyhole/metric/__init__.py
gr_pyhole/metric/base.py
gr_pyhole/metric/flat.py
gr_pyhole/metric/hr.py
gr_pyhole/metric/kerr.py
gr_pyhole/metric/schwarzschild.py
gr_pyhole/observer/__init__.py
gr_pyhole/observer/equirectangular.py
gr_pyhole/observer/gnomonic.py
gr_pyhole/observer/observer.py
gr_pyhole/observer/stereographic.py
gr_pyhole/propagator/__init__.py
gr_pyhole/propagator/cpu.py
gr_pyhole/propagator/gpu.py
gr_pyhole/propagator/propagator.py
